nonebot_plugin_xdu_support/__init__.py
nonebot_plugin_xdu_support/config.py
nonebot_plugin_xdu_support/data_source.py
nonebot_plugin_xdu_support/energy.py
nonebot_plugin_xdu_support/model.py
nonebot_plugin_xdu_support/physic.py
nonebot_plugin_xdu_support/playwright_integration.py
nonebot_plugin_xdu_support/record2txt.py
nonebot_plugin_xdu_support/txt2img.py
nonebot_plugin_xdu_support/data/TXT2IMG/font/sarasa-mono-sc-regular.ttf
nonebot_plugin_xdu_support/data/TXT2IMG/image/background.png
nonebot_plugin_xdu_support/data/TXT2IMG/image/banner.png
nonebot_plugin_xdu_support/data/TXT2IMG/image/mi_background.png
nonebot_plugin_xdu_support-0.6.2.dist-info/LICENSE
nonebot_plugin_xdu_support-0.6.2.dist-info/METADATA
nonebot_plugin_xdu_support-0.6.2.dist-info/WHEEL
nonebot_plugin_xdu_support-0.6.2.dist-info/top_level.txt
nonebot_plugin_xdu_support-0.6.2.dist-info/RECORD
