Metadata-Version: 2.1
Name: nonebot-plugin-xdu-support
Version: 0.6.2
Summary: A plugin based on nonebot2, which is support XDU services.
Home-page: http://lcgx.xdu.org.cn/
Author: longchengguxiao
Author-email: 1298919732@qq.com
License: AGPL-3.0 License
Platform: all
Classifier: Intended Audience :: Developers
Classifier: Operating System :: OS Independent
Classifier: Natural Language :: Chinese (Simplified)
Classifier: Programming Language :: Python
Classifier: Programming Language :: Python :: 3.8
Classifier: Programming Language :: Python :: 3.9
Classifier: Topic :: Software Development :: Libraries
License-File: LICENSE
Requires-Dist: nonebot2 (>=2.0.0a16)
Requires-Dist: nonebot-adapter-onebot (>=2.0.0b1)
Requires-Dist: nonebot-plugin-apscheduler (>=0.2.0)
Requires-Dist: requests
Requires-Dist: libxduauth (>=1.7.4)
Requires-Dist: pytz
Requires-Dist: lxml
Requires-Dist: pyDes
Requires-Dist: httpx
Requires-Dist: numpy
Requires-Dist: jionlp
Requires-Dist: pycryptodome
Requires-Dist: python-dateutil
Requires-Dist: setuptools
Requires-Dist: jieba
Requires-Dist: pilk
Requires-Dist: ddddocr (>=1.4.7)
